hexabyte/__init__.py
hexabyte/__main__.py
hexabyte/actions/__init__.py
hexabyte/actions/_action.py
hexabyte/actions/action_handler.py
hexabyte/actions/api/__init__.py
hexabyte/actions/api/_api_action.py
hexabyte/actions/api/clear.py
hexabyte/actions/api/delete.py
hexabyte/actions/api/find.py
hexabyte/actions/api/goto.py
hexabyte/actions/api/highlight.py
hexabyte/actions/api/insert.py
hexabyte/actions/api/move.py
hexabyte/actions/api/open.py
hexabyte/actions/api/redo.py
hexabyte/actions/api/replace.py
hexabyte/actions/api/revert.py
hexabyte/actions/api/save.py
hexabyte/actions/api/save_as.py
hexabyte/actions/api/select.py
hexabyte/actions/api/set.py
hexabyte/actions/api/undo.py
hexabyte/actions/api/unhighlight.py
hexabyte/actions/app/__init__.py
hexabyte/actions/app/_app_action.py
hexabyte/actions/app/exit.py
hexabyte/actions/command_prompt/__init__.py
hexabyte/api.py
hexabyte/commands/__init__.py
hexabyte/commands/command.py
hexabyte/commands/command_parser.py
hexabyte/commands/decorators.py
hexabyte/config.py
hexabyte/constants/__init__.py
hexabyte/constants/enums.py
hexabyte/constants/generic.py
hexabyte/constants/sizes.py
hexabyte/context.py
hexabyte/cursor.py
hexabyte/data_sources/__init__.py
hexabyte/data_sources/_data_source.py
hexabyte/data_sources/data_block.py
hexabyte/data_sources/paged_data_source.py
hexabyte/data_sources/simple_data_source.py
hexabyte/data_types.py
hexabyte/hexabyte_app.css
hexabyte/hexabyte_app.py
hexabyte/plugins.py
hexabyte/utils/__init__.py
hexabyte/utils/data_manipulation.py
hexabyte/view_components/__init__.py
hexabyte/view_components/byte_view.py
hexabyte/view_components/hc_view.py
hexabyte/widgets/__init__.py
hexabyte/widgets/command_prompt.py
hexabyte/widgets/editor.py
hexabyte/widgets/help_screen.py
hexabyte/widgets/info_panel.py
hexabyte/widgets/sidebar.py
hexabyte/widgets/sidebar_panel.py
hexabyte/widgets/workbench.py
hexabyte-0.8.7.dist-info/LICENSE
hexabyte-0.8.7.dist-info/METADATA
hexabyte-0.8.7.dist-info/WHEEL
hexabyte-0.8.7.dist-info/entry_points.txt
hexabyte-0.8.7.dist-info/RECORD
