Metadata-Version: 2.1
Name: hexabyte
Version: 0.8.7
Summary: A modern, modular, and robust TUI hex editor.
Home-page: https://github.com/thetacom/hexabyte
Keywords: commandline,hexeditor,binary,hexadecimal,raw,byteview,bytes
Author: Justin C
Author-email: justin@thetacom.info
Requires-Python: >=3.9,<4.0
Classifier: Development Status :: 3 - Alpha
Classifier: Environment :: Console
Classifier: Intended Audience :: Developers
Classifier: Intended Audience :: Information Technology
Classifier: Intended Audience :: Science/Research
Classifier: Intended Audience :: System Administrators
Classifier: License :: OSI Approved :: GNU General Public License v3 (GPLv3)
Classifier: Natural Language :: English
Classifier: Operating System :: MacOS :: MacOS X
Classifier: Operating System :: Microsoft :: Windows
Classifier: Operating System :: POSIX :: Linux
Classifier: Programming Language :: Python
Classifier: Programming Language :: Python :: 3
Classifier: Programming Language :: Python :: 3.9
Classifier: Programming Language :: Python :: 3.10
Classifier: Programming Language :: Python :: 3.11
Classifier: Programming Language :: Python :: 3.12
Classifier: Programming Language :: Python :: 3 :: Only
Classifier: Programming Language :: Python :: Implementation :: CPython
Classifier: Topic :: Software Development
Classifier: Topic :: Utilities
Requires-Dist: hilbertcurve (>=2.0.5,<3.0.0)
Requires-Dist: munch (>=4.0.0,<5.0.0)
Requires-Dist: textual (>=0.53.1,<0.54.0)
Requires-Dist: toml (>=0.10.2,<0.11.0)
Project-URL: Repository, https://github.com/thetacom/hexabyte
